{
  "build": {
    "content": [
      {
        "files": [
          "**/*.md",
          "**/*.yml"
        ],
        "exclude": [
          "**/obj/**",
          "**/includes/**",
          "_themes/**",
          "_themes.pdf/**",
          "**/docfx.json",
          "README.md",
          "LICENSE",
          "LICENSE-CODE",
          "ThirdPartyNotices"
        ]
      }
    ],
    "resource": [
      {
        "files": [
          "**/*.png",
          "**/*.jpg"
        ],
        "exclude": [
          "**/obj/**",
          "**/includes/**",
          "_themes/**",
          "_themes.pdf/**",
          "**/docfx.json"
        ]
      }
    ],
    "overwrite": [],
    "externalReference": [],
    "globalMetadata": {
      "uhfHeaderId": "MSDocsHeader-PowerPlatform",
      "breadcrumb_path": "/data-integration/breadcrumb/toc.json",
      "feedback_system": "Standard",
      "feedback_product_url": "https://ideas.fabric.microsoft.com/?forum=2d80fd4a-16cb-4189-896b-e0dac5e08b41",
      "feedback_help_link_url": "https://community.fabric.microsoft.com/t5/Forums/ct-p/PBI_Comm_Forums",
      "feedback_help_link_type": "ask-the-community",
      "recommendations": true,
      "ms.service": "data-integration-gateways"
    },
    "fileMetadata": {
      "ms.author":{
        "vnet/**.*": "dougklo",
        "gateway/**.*": "dougklo"
      },
      "author":{
        "vnet/**.*": "nikkiwaghani",
        "gateway/**.*": "nikkiwaghani"
      },
      "ms.subservice":{
        "vnet/**.*": "virtual-network-data-gateways",
        "gateway/**.*": "on-premises-data-gateways"
      }
    },
    "template": [],
    "dest": "data-integration",
    "markdownEngineName": "markdig"
  }
}
